funpay_scrapper/__init__.py
funpay_scrapper/chips.py
funpay_scrapper/lots.py
funpay_scrapper/offers.py
funpay_scrapper/profile.py
funpay_scrapper/utils.py
funpay_scrapper-0.1.3.dist-info/LICENSE
funpay_scrapper-0.1.3.dist-info/METADATA
funpay_scrapper-0.1.3.dist-info/WHEEL
funpay_scrapper-0.1.3.dist-info/top_level.txt
funpay_scrapper-0.1.3.dist-info/RECORD
