Metadata-Version: 2.1
Name: funpay-scrapper
Version: 0.1.3
Summary: Funpay Scraper
Home-page: https://github.com/KailUser/funpay-scrapper
Author: Syirezz
Author-email: syirezz@icloud.com
Classifier: Programming Language :: Python :: 3
Classifier: License :: OSI Approved :: MIT License
Classifier: Operating System :: OS Independent
Requires-Python: >=3.6
License-File: LICENSE
Requires-Dist: beautifulsoup4
Requires-Dist: requests
